LICENSE
MANIFEST.in
README.rst
pyproject.toml
setup.py
admin_torcms/__init__.py
admin_torcms/admin.py
admin_torcms/apps.py
admin_torcms/models.py
admin_torcms/tests.py
admin_torcms/views.py
admin_torcms/management/__init__.py
admin_torcms/management/commands/__init__.py
admin_torcms/management/commands/clear_data.py
admin_torcms/management/commands/init_app.py
admin_torcms/management/commands/reset_db.py
admin_torcms/migrations/__init__.py
administor/__init__.py
administor/asgi.py
administor/settings.py
administor/urls.py
administor/wsgi.py
torcms/__init__.py
torcms.egg-info/PKG-INFO
torcms.egg-info/SOURCES.txt
torcms.egg-info/dependency_links.txt
torcms.egg-info/requires.txt
torcms.egg-info/top_level.txt
torcms.egg-info/zip-safe
torcms/core/__init__.py
torcms/core/base_handler.py
torcms/core/base_model.py
torcms/core/privilege.py
torcms/core/router.py
torcms/core/tools.py
torcms/core/torcms_redis.py
torcms/core/uifunction.py
torcms/core/tool/__init__.py
torcms/core/tool/send_email.py
torcms/core/tool/sqlite_helper.py
torcms/core/tool/whoosh_tool.py
torcms/handlers/__init__.py
torcms/handlers/admin_handler.py
torcms/handlers/catalog_hander.py
torcms/handlers/category_handler.py
torcms/handlers/check_handler.py
torcms/handlers/classify_hander.py
torcms/handlers/collect_handler.py
torcms/handlers/comment_hander.py
torcms/handlers/entity2user_handler.py
torcms/handlers/entity_handler.py
torcms/handlers/evaluation_handler.py
torcms/handlers/filter_handler.py
torcms/handlers/index.py
torcms/handlers/label_handler.py
torcms/handlers/leaf_handler.py
torcms/handlers/link_handler.py
torcms/handlers/list_handler.py
torcms/handlers/log_handler.py
torcms/handlers/nullify_info_handler.py
torcms/handlers/page_ajax_handler.py
torcms/handlers/page_handler.py
torcms/handlers/post_ajax_handler.py
torcms/handlers/post_handler.py
torcms/handlers/post_history_handler.py
torcms/handlers/post_list_handler.py
torcms/handlers/publish_handler.py
torcms/handlers/rating_handler.py
torcms/handlers/referrer_handler.py
torcms/handlers/relation_handler.py
torcms/handlers/reply_handler.py
torcms/handlers/search_handler.py
torcms/handlers/static_handler.py
