Metadata-Version: 2.1
Name: torcms
Version: 0.9.1
Summary: Flexible, extensible Web CMS framework built on Tornado,compatible with Python 3.9 and above.
Home-page: https://github.com/bukun/TorCMS
Author: bukun
Author-email: bukun@osgeo.cn
License: MIT License
Keywords: torcms,tornado,cms
Platform: any
Classifier: Development Status :: 3 - Alpha
Classifier: Intended Audience :: Developers
Classifier: Topic :: Software Development :: Libraries :: Python Modules
Classifier: License :: OSI Approved :: MIT License
Classifier: Programming Language :: Python :: 3
Classifier: Programming Language :: Python :: 3.9
Classifier: Programming Language :: Python :: 3.10
Classifier: Programming Language :: Python :: 3.11
Classifier: Programming Language :: Python :: 3.12
Classifier: Programming Language :: Python :: 3.13
License-File: LICENSE
